golum/__init__.py
golum/lookup/__init__.py
golum/lookup/lookup.py
golum/pe/__init__.py
golum/pe/likelihood.py
golum/pe/prior.py
golum/population/__init__.py
golum/population/lensingstatistics.py
golum/population/snronpairs_quad_dbl.py
golum/population/statistics_models/Rgal_dt.txt
golum/population/statistics_models/out_fincat_AL/all_lensprop.txt
golum/population/statistics_models/out_fincat_AL/dblall_imgprop.txt
golum/population/statistics_models/out_fincat_AL/quadall_imgprop.txt
golum/population/statistics_models/out_fincat_Ap/all_lensprop.txt
golum/population/statistics_models/out_fincat_Ap/dblall_imgprop.txt
golum/population/statistics_models/out_fincat_Ap/quadall_imgprop.txt
golum/population/statistics_models/out_fincat_CE/all_lensprop.txt
golum/population/statistics_models/out_fincat_CE/dblall_imgprop.txt
golum/population/statistics_models/out_fincat_CE/quadall_imgprop.txt
golum/population/statistics_models/out_fincat_ET/all_lensprop.txt
golum/population/statistics_models/out_fincat_ET/dblall_imgprop.txt
golum/population/statistics_models/out_fincat_ET/quadall_imgprop.txt
golum/population/statistics_models/out_fincat_O3/all_lensprop.txt
golum/population/statistics_models/out_fincat_O3/dblall_imgprop.txt
golum/population/statistics_models/out_fincat_O3/quadall_imgprop.txt
golum/population/statistics_models/unlensedpairs/unlensedpairs_tdmag_AL.txt
golum/population/statistics_models/unlensedpairs/unlensedpairs_tdmag_Ap.txt
golum/population/statistics_models/unlensedpairs/unlensedpairs_tdmag_CE.txt
golum/population/statistics_models/unlensedpairs/unlensedpairs_tdmag_ET.txt
golum/population/statistics_models/unlensedpairs/unlensedpairs_tdmag_O3.txt
golum/population/statistics_models/unlensedpop/all_bbh_unlensprop_O3.txt
golum/population/statistics_models/unlensedpop/get_unlensedpairs.py
golum/population/statistics_models/unlensedpop/getcat_unlens4lenspop.txt
golum/tools/__init__.py
golum/tools/conversion.py
golum/tools/postprocessing.py
golum/tools/utils.py
golum-1.0.1.dist-info/LICENSE
golum-1.0.1.dist-info/METADATA
golum-1.0.1.dist-info/WHEEL
golum-1.0.1.dist-info/top_level.txt
golum-1.0.1.dist-info/RECORD
